{
  "code": "5E2",
  "security_type": "share",
  "currency": "SGD",
  "last_updated": "2026-06-29T22:48:24.771541+00:00",
  "short_history": [],
  "connect_flows": null,
  "daily_turnover": [
    {
      "date": "2026-06-25",
      "volume": 9968097,
      "value_sgd": 19537470.5
    },
    {
      "date": "2026-06-26",
      "volume": 11271000,
      "value_sgd": 21978450.54
    },
    {
      "date": "2026-06-29",
      "volume": 9928900,
      "value_sgd": 19361355.47
    }
  ],
  "short_selling_eligible": true
}