{
  "code": "QNS",
  "security_type": "share",
  "currency": "SGD",
  "last_updated": "2026-06-30T23:07:24.909138+00:00",
  "short_history": [],
  "connect_flows": null,
  "daily_turnover": [
    {
      "date": "2026-06-25",
      "volume": 186600,
      "value_sgd": 80238.0
    },
    {
      "date": "2026-06-26",
      "volume": 98900,
      "value_sgd": 42527.0
    },
    {
      "date": "2026-06-29",
      "volume": 30000,
      "value_sgd": 12900.0
    },
    {
      "date": "2026-06-30",
      "volume": 86100,
      "value_sgd": 37023.0
    }
  ],
  "short_selling_eligible": false
}