{
  "code": "BIX",
  "name": "ELLIPSIZ LTD",
  "security_type": "share",
  "currency": "SGD",
  "last_updated": "2026-06-25T18:41:34.080006+00:00",
  "free_float_pct": null,
  "consistency_score": null,
  "signal": null,
  "mandate": {},
  "summary": {},
  "daily_returns": [],
  "issuances": [],
  "results_dates": [
    {
      "date": "2025-08-27T10:02:58+00:00",
      "type": "annual",
      "filing_url": "https://links.sgx.com/1.0.0/corporate-announcements/74X55SFIWIYCMJLD/082953bbc4f0ad4f83a431cf946f5f34e9c83d6f35ed8fcbb6c45ca133ab1a51"
    }
  ]
}