{
  "code": "E3B",
  "name": "WEE HUR HOLDINGS LTD.",
  "security_type": "share",
  "currency": "SGD",
  "last_updated": "2026-06-25T18:27:32.048218+00:00",
  "free_float_pct": null,
  "consistency_score": null,
  "signal": null,
  "mandate": {},
  "summary": {},
  "daily_returns": [],
  "issuances": [],
  "results_dates": [
    {
      "date": "2025-08-14T13:50:02+00:00",
      "type": "other",
      "filing_url": "https://links.sgx.com/1.0.0/corporate-announcements/UP0Z1L9B6HAW9KW8/73a9cd54cacacab1e4e10e9de308658e04feb5e8ba1b5b5f3f49c413ac21daec"
    }
  ]
}