{
  "code": "JK8",
  "name": "UOB ASSET MANAGEMENT LTD",
  "security_type": "share",
  "currency": "SGD",
  "last_updated": "2026-06-25T18:59:49.779497+00:00",
  "free_float_pct": null,
  "consistency_score": null,
  "signal": null,
  "mandate": {},
  "summary": {},
  "daily_returns": [],
  "issuances": [],
  "results_dates": [
    {
      "date": "2025-09-25T00:13:36+00:00",
      "type": "annual",
      "filing_url": "https://links.sgx.com/1.0.0/corporate-announcements/UHCP0J7ZM6ZWVHB8/0914daf5c358cdfa33282997426d53640b67128767a2aa76bb7791dbb3e1fbac"
    }
  ]
}