[
  {
    "filing_date": "2026-06-23",
    "code": "00268",
    "stock_name": "KINGDEE INTERNATIONAL SOFTWARE GROUP CO. LTD.",
    "shareholder": "富国基金管理有限公司",
    "notice_type": "Change",
    "long_position_pct": 4.97,
    "form_type": "Form 2",
    "relevant_event_date": "2026-06-18"
  },
  {
    "filing_date": "2026-06-23",
    "code": "00356",
    "stock_name": "DT CAPITAL LTD.",
    "shareholder": "Chan Pui Kwan",
    "notice_type": "Change",
    "long_position_pct": 8.42,
    "form_type": "Form 3A",
    "relevant_event_date": "2026-06-23"
  },
  {
    "filing_date": "2026-06-23",
    "code": "00356",
    "stock_name": "DT CAPITAL LTD.",
    "shareholder": "Ho Hoi Yee Wisery",
    "notice_type": "Change",
    "long_position_pct": 8.42,
    "form_type": "Form 1",
    "relevant_event_date": "2026-06-23"
  },
  {
    "filing_date": "2026-06-23",
    "code": "00356",
    "stock_name": "DT CAPITAL LTD.",
    "shareholder": "Lai Tsui Har",
    "notice_type": "Change",
    "long_position_pct": 8.42,
    "form_type": "Form 2",
    "relevant_event_date": "2026-06-23"
  },
  {
    "filing_date": "2026-06-23",
    "code": "00428",
    "stock_name": "COCOON HOLDINGS LTD.",
    "shareholder": "YU PO KWAN",
    "notice_type": "Change",
    "long_position_pct": 22.28,
    "form_type": "Form 1",
    "relevant_event_date": "2026-06-22"
  },
  {
    "filing_date": "2026-06-23",
    "code": "00585",
    "stock_name": "IMAGI INTERNATIONAL HOLDINGS LTD.",
    "shareholder": "Goldpalm Offshore Limited",
    "notice_type": "Change",
    "long_position_pct": 10.0,
    "form_type": "Form 2",
    "relevant_event_date": "2026-04-18"
  },
  {
    "filing_date": "2026-06-23",
    "code": "00585",
    "stock_name": "IMAGI INTERNATIONAL HOLDINGS LTD.",
    "shareholder": "MA YANYING",
    "notice_type": "Change",
    "long_position_pct": 10.0,
    "form_type": "Form 1",
    "relevant_event_date": "2026-04-18"
  },
  {
    "filing_date": "2026-06-23",
    "code": "00701",
    "stock_name": "CNT GROUP LTD.",
    "shareholder": "Ho Mei Po, Mabel",
    "notice_type": "Change",
    "long_position_pct": 50.17,
    "form_type": "Form 1",
    "relevant_event_date": "2026-06-17"
  },
  {
    "filing_date": "2026-06-23",
    "code": "00701",
    "stock_name": "CNT GROUP LTD.",
    "shareholder": "Prime Surplus Limited",
    "notice_type": "Change",
    "long_position_pct": 50.17,
    "form_type": "Form 2",
    "relevant_event_date": "2026-06-17"
  },
  {
    "filing_date": "2026-06-23",
    "code": "00701",
    "stock_name": "CNT GROUP LTD.",
    "shareholder": "Tsui Ho Chuen, Philip",
    "notice_type": "Change",
    "long_position_pct": 50.17,
    "form_type": "Form 3A",
    "relevant_event_date": "2026-06-17"
  },
  {
    "filing_date": "2026-06-23",
    "code": "00826",
    "stock_name": "TIANGONG INTERNATIONAL CO. LTD.",
    "shareholder": "Niu Qiu Ping",
    "notice_type": "Change",
    "long_position_pct": 25.35,
    "form_type": "Form 1",
    "relevant_event_date": "2026-01-20"
  },
  {
    "filing_date": "2026-06-23",
    "code": "00826",
    "stock_name": "TIANGONG INTERNATIONAL CO. LTD.",
    "shareholder": "Yu Yumei",
    "notice_type": "Change",
    "long_position_pct": 29.05,
    "form_type": "Form 1",
    "relevant_event_date": "2026-01-20"
  },
  {
    "filing_date": "2026-06-23",
    "code": "00826",
    "stock_name": "TIANGONG INTERNATIONAL CO. LTD.",
    "shareholder": "Zhu Xiaokun",
    "notice_type": "Change",
    "long_position_pct": 29.05,
    "form_type": "Form 3A",
    "relevant_event_date": "2026-01-20"
  },
  {
    "filing_date": "2026-06-23",
    "code": "00826",
    "stock_name": "TIANGONG INTERNATIONAL CO. LTD.",
    "shareholder": "Zhu Zefeng",
    "notice_type": "Change",
    "long_position_pct": 25.35,
    "form_type": "Form 3A",
    "relevant_event_date": "2026-01-20"
  },
  {
    "filing_date": "2026-06-23",
    "code": "00884",
    "stock_name": "CIFI HOLDINGS (GROUP) CO. LTD.",
    "shareholder": "Ding Chang Limited",
    "notice_type": "Change",
    "long_position_pct": 7.51,
    "form_type": "Form 2",
    "relevant_event_date": "2026-06-17"
  },
  {
    "filing_date": "2026-06-23",
    "code": "00884",
    "stock_name": "CIFI HOLDINGS (GROUP) CO. LTD.",
    "shareholder": "Eternally Success International Limited 永成國際有限公司",
    "notice_type": "Change",
    "long_position_pct": 7.51,
    "form_type": "Form 2",
    "relevant_event_date": "2026-06-17"
  },
  {
    "filing_date": "2026-06-23",
    "code": "00884",
    "stock_name": "CIFI HOLDINGS (GROUP) CO. LTD.",
    "shareholder": "Gentle Beauty Assets Limited",
    "notice_type": "Change",
    "long_position_pct": 22.4,
    "form_type": "Form 2",
    "relevant_event_date": "2026-06-17"
  },
  {
    "filing_date": "2026-06-23",
    "code": "00884",
    "stock_name": "CIFI HOLDINGS (GROUP) CO. LTD.",
    "shareholder": "LIN Feng",
    "notice_type": "Change",
    "long_position_pct": 23.58,
    "form_type": "Form 1",
    "relevant_event_date": "2026-06-17"
  },
  {
    "filing_date": "2026-06-23",
    "code": "00884",
    "stock_name": "CIFI HOLDINGS (GROUP) CO. LTD.",
    "shareholder": "LIN Wei",
    "notice_type": "Change",
    "long_position_pct": 25.18,
    "form_type": "Form 3A",
    "relevant_event_date": "2026-06-17"
  },
  {
    "filing_date": "2026-06-23",
    "code": "00884",
    "stock_name": "CIFI HOLDINGS (GROUP) CO. LTD.",
    "shareholder": "LIN Zhong",
    "notice_type": "Change",
    "long_position_pct": 42.19,
    "form_type": "Form 3A",
    "relevant_event_date": "2026-06-17"
  },
  {
    "filing_date": "2026-06-23",
    "code": "00884",
    "stock_name": "CIFI HOLDINGS (GROUP) CO. LTD.",
    "shareholder": "Rosy Fortune Investments Limited",
    "notice_type": "Change",
    "long_position_pct": 22.4,
    "form_type": "Form 2",
    "relevant_event_date": "2026-06-17"
  },
  {
    "filing_date": "2026-06-23",
    "code": "00884",
    "stock_name": "CIFI HOLDINGS (GROUP) CO. LTD.",
    "shareholder": "SCTS Capital Pte. Ltd.",
    "notice_type": "Change",
    "long_position_pct": 30.99,
    "form_type": "Form 2",
    "relevant_event_date": "2026-06-17"
  },
  {
    "filing_date": "2026-06-23",
    "code": "00884",
    "stock_name": "CIFI HOLDINGS (GROUP) CO. LTD.",
    "shareholder": "Standard Chartered Trust (Singapore) Limited",
    "notice_type": "Change",
    "long_position_pct": 30.99,
    "form_type": "Form 2",
    "relevant_event_date": "2026-06-17"
  },
  {
    "filing_date": "2026-06-23",
    "code": "01020",
    "stock_name": "CIPRUN TECHNOLOGY HOLDINGS CO. LTD.",
    "shareholder": "CIPRUN INTERNATIONAL LIMITED",
    "notice_type": "Change",
    "long_position_pct": 27.66,
    "form_type": "Form 2",
    "relevant_event_date": "2026-06-17"
  },
  {
    "filing_date": "2026-06-23",
    "code": "01020",
    "stock_name": "CIPRUN TECHNOLOGY HOLDINGS CO. LTD.",
    "shareholder": "CIPRUN LIMITED",
    "notice_type": "Change",
    "long_position_pct": 27.66,
    "form_type": "Form 2",
    "relevant_event_date": "2026-06-17"
  },
  {
    "filing_date": "2026-06-23",
    "code": "01020",
    "stock_name": "CIPRUN TECHNOLOGY HOLDINGS CO. LTD.",
    "shareholder": "Kong Junmin",
    "notice_type": "Change",
    "long_position_pct": 27.66,
    "form_type": "Form 3A",
    "relevant_event_date": "2026-06-17"
  },
  {
    "filing_date": "2026-06-23",
    "code": "01140",
    "stock_name": "HK.AI CAPITAL LTD.",
    "shareholder": "Acorn Harvest Holdings Limited",
    "notice_type": "Increase",
    "long_position_pct": 5.95,
    "form_type": "Form 2",
    "relevant_event_date": "2026-06-22"
  },
  {
    "filing_date": "2026-06-23",
    "code": "01140",
    "stock_name": "HK.AI CAPITAL LTD.",
    "shareholder": "YANG Fan",
    "notice_type": "Increase",
    "long_position_pct": 5.95,
    "form_type": "Form 1",
    "relevant_event_date": "2026-06-22"
  },
  {
    "filing_date": "2026-06-23",
    "code": "01208",
    "stock_name": "MMG LTD.",
    "shareholder": "中國五礦香港控股有限公司",
    "notice_type": "Change",
    "long_position_pct": 63.72,
    "form_type": "Form 2",
    "relevant_event_date": "2026-06-23"
  },
  {
    "filing_date": "2026-06-23",
    "code": "01234",
    "stock_name": "CHINA LILANG LTD.",
    "shareholder": "Xiao Sheng International Limited",
    "notice_type": "Change",
    "long_position_pct": 59.02,
    "form_type": "Form 2",
    "relevant_event_date": "2026-06-18"
  }
]